skill_data_controls/LICENSE.md
skill_data_controls/README.md
skill_data_controls/__init__.py
skill_data_controls/skill.json
skill_data_controls/version.py
skill_data_controls/locale/en-us/dialog/ask_clear_data.dialog
skill_data_controls/locale/en-us/dialog/confirm_clear_all.dialog
skill_data_controls/locale/en-us/dialog/confirm_clear_data.dialog
skill_data_controls/locale/en-us/dialog/confirm_no_action.dialog
skill_data_controls/locale/en-us/dialog/word_all_brands.dialog
skill_data_controls/locale/en-us/dialog/word_all_data.dialog
skill_data_controls/locale/en-us/dialog/word_caches.dialog
skill_data_controls/locale/en-us/dialog/word_disliked_brands.dialog
skill_data_controls/locale/en-us/dialog/word_language.dialog
skill_data_controls/locale/en-us/dialog/word_liked_brands.dialog
skill_data_controls/locale/en-us/dialog/word_media.dialog
skill_data_controls/locale/en-us/dialog/word_profile_data.dialog
skill_data_controls/locale/en-us/dialog/word_transcriptions.dialog
skill_data_controls/locale/en-us/dialog/word_units.dialog
skill_data_controls/locale/en-us/intent/clear_data.intent
skill_data_controls/locale/en-us/vocab/brands.voc
skill_data_controls/locale/en-us/vocab/cache.voc
skill_data_controls/locale/en-us/vocab/cancel.voc
skill_data_controls/locale/en-us/vocab/data.voc
skill_data_controls/locale/en-us/vocab/dislikes.voc
skill_data_controls/locale/en-us/vocab/language.voc
skill_data_controls/locale/en-us/vocab/likes.voc
skill_data_controls/locale/en-us/vocab/media.voc
skill_data_controls/locale/en-us/vocab/profile.voc
skill_data_controls/locale/en-us/vocab/transcription.voc
skill_data_controls/locale/en-us/vocab/units.voc
skill_data_controls/neon_skill_data_controls.egg-info/PKG-INFO
skill_data_controls/neon_skill_data_controls.egg-info/SOURCES.txt
skill_data_controls/neon_skill_data_controls.egg-info/dependency_links.txt
skill_data_controls/neon_skill_data_controls.egg-info/entry_points.txt
skill_data_controls/neon_skill_data_controls.egg-info/requires.txt
skill_data_controls/neon_skill_data_controls.egg-info/top_level.txt
skill_data_controls/test/test_skill.py
neon_skill_data_controls-2.0.3.dist-info/LICENSE.md
neon_skill_data_controls-2.0.3.dist-info/METADATA
neon_skill_data_controls-2.0.3.dist-info/WHEEL
neon_skill_data_controls-2.0.3.dist-info/entry_points.txt
neon_skill_data_controls-2.0.3.dist-info/top_level.txt
neon_skill_data_controls-2.0.3.dist-info/RECORD
